helga_pika
